serialization_tools/__init__.py
serialization_tools/common_directories.py
serialization_tools/error.py
serialization_tools/ioutil.py
serialization_tools/magic.py
serialization_tools/size.py
serialization_tools/structx.py
serialization_tools/vstruct.py
serialization_tools/walkutil.py
mak_serialization_tools-2022.0a19.dist-info/LICENSE.txt
mak_serialization_tools-2022.0a19.dist-info/METADATA
mak_serialization_tools-2022.0a19.dist-info/WHEEL
mak_serialization_tools-2022.0a19.dist-info/top_level.txt
mak_serialization_tools-2022.0a19.dist-info/RECORD
