Metadata-Version: 2.1
Name: mak-serialization-tools
Version: 2022.0a19
Summary: A small collection of tools for unpacking/packing data
Home-page: https://github.com/ModernMAK/Serialization-Tools
Author: Marcus Kertesz
License: UNKNOWN
Project-URL: Bug Tracker, https://github.com/ModernMAK/Serialization-Tools/issues
Platform: UNKNOWN
Classifier: Programming Language :: Python :: 3
Classifier: License :: OSI Approved :: MIT License
Requires-Python: >=3.9
License-File: LICENSE.txt
